bl/__init__.py
bl/base.py
bl/config.py
bl/csv.py
bl/dict.py
bl/file.py
bl/folder.py
bl/id.py
bl/int.py
bl/json.py
bl/no.py
bl/progress.py
bl/pwd.py
bl/rglob.py
bl/string.py
bl/text.py
bl/url.py
bl/zip.py
bl-2.4.0.dist-info/LICENSE
bl-2.4.0.dist-info/METADATA
bl-2.4.0.dist-info/WHEEL
bl-2.4.0.dist-info/top_level.txt
bl-2.4.0.dist-info/RECORD
