Metadata-Version: 2.1
Name: bl
Version: 2.4.0
Summary: Black Earth core library
Home-page: https://github.com/BlackEarth/bl
Author: Sean Harrison
Author-email: sah@bookgenesis.com
License: MPL 2.0
Platform: UNKNOWN
Classifier: Development Status :: 5 - Production/Stable
Classifier: Intended Audience :: Developers
Classifier: License :: OSI Approved :: Mozilla Public License 2.0 (MPL 2.0)
Classifier: Programming Language :: Python :: 2
Classifier: Programming Language :: Python :: 3
Provides-Extra: dev
Requires-Dist: twine ; extra == 'dev'
Provides-Extra: test
